cursecord/__init__.py
cursecord/py.typed
cursecord-0.1.0.dist-info/LICENSE
cursecord-0.1.0.dist-info/WHEEL
cursecord-0.1.0.dist-info/METADATA
cursecord-0.1.0.dist-info/RECORD
