Metadata-Version: 2.1
Name: cursecord
Version: 0.1.0
Summary: Why
Home-page: https://github.com/an-dyy/Cursecord
License: MIT
Keywords: discord
Author: andy
Author-email: andy.development@protonmail.com
Requires-Python: >=3.9,<4.0
Classifier: License :: OSI Approved :: MIT License
Classifier: Programming Language :: Python :: 3
Classifier: Programming Language :: Python :: 3.10
Classifier: Programming Language :: Python :: 3.9
Requires-Dist: aiohttp (>=3.8.1,<4.0.0)
Requires-Dist: fishhook (>=0.1.4,<0.2.0)
Requires-Dist: typing-extensions (>=4.1.1,<5.0.0)
